{
  "id": "3604",
  "author": "kanan",
  "email_hash": "a79889037a92550fade481994d1c643b",
  "url": "http://www.peopleoftheworld.photography/",
  "date": "2019-08-27 21:19:54",
  "content": "I have another idea.\n\nRegister a complaint with Malaysian Communications and Multimedia Commission\n\nhttp://www.skmm.gov.my/Resources/Guidelines/Complaints-Handling-Resolution.aspx\n\nIf they receive a few complaints maybe they will do something to pull YES into line and stop them from ripping us all off"
}