{
  "id": "4026",
  "author": "Ain Nia",
  "email_hash": "6c8d2bd30f2234347da8ff44e8427927",
  "url": null,
  "date": "2019-08-28 23:10:33",
  "content": "Hi kar2on,\nNow I realize what my aim to build blog is because I want share with others about my passion and lifestyle with some earn of money or get any sponsor. Why I write to you is because on that time I really need money so I looked at my nuffnang and think I should earn from this but get disappointing when nuffnang doesn't credit based on my unique visitors. But now I understand, thank you for your concerned. Please support my blog so my blog traffic grow and I will became patient. =)"
}